xontrib_1password/__init__.py
xontrib_1password/__version__.py
xontrib_1password/main.py
xontrib_1password-0.3.1.dist-info/LICENSE
xontrib_1password-0.3.1.dist-info/METADATA
xontrib_1password-0.3.1.dist-info/WHEEL
xontrib_1password-0.3.1.dist-info/entry_points.txt
xontrib_1password-0.3.1.dist-info/RECORD
