Metadata-Version: 2.3
Name: xontrib-1password
Version: 0.3.1
Summary: 1password support for xonsh
License: MIT
Keywords: xontrib,xonsh
Author: Mike Crowe
Author-email: drmikecrowe@gmail.com
Requires-Python: >=3.8
Classifier: Intended Audience :: Developers
Classifier: License :: OSI Approved :: MIT License
Classifier: Natural Language :: English
Classifier: Operating System :: OS Independent
Classifier: Programming Language :: Python :: 3
Classifier: Programming Language :: Python :: 3.8
Classifier: Programming Language :: Python :: 3.9
Classifier: Programming Language :: Python :: 3.10
Classifier: Programming Language :: Python :: 3.11
Classifier: Programming Language :: Python :: 3.12
Classifier: Programming Language :: Python :: 3.13
Classifier: Topic :: System :: Shells
Classifier: Topic :: System :: System Shells
Classifier: Topic :: Terminals
Requires-Dist: xonsh (>=0.12.5)
Project-URL: Code, https://github.com/drmikecrowe/xontrib-1password
Project-URL: Documentation, https://github.com/drmikecrowe/xontrib-1password/blob/master/README.md
Project-URL: Homepage, https://github.com/drmikecrowe/xontrib-1password
Project-URL: Issue tracker, https://github.com/drmikecrowe/xontrib-1password/issues
Project-URL: Repository, https://github.com/drmikecrowe/xontrib-1password
